font_to_py/__init__.py
font_to_py/font_to_py.py
font_to_py-0.44.2.dist-info/licenses/LICENSE
font_to_py-0.44.2.dist-info/METADATA
font_to_py-0.44.2.dist-info/WHEEL
font_to_py-0.44.2.dist-info/entry_points.txt
font_to_py-0.44.2.dist-info/top_level.txt
font_to_py-0.44.2.dist-info/RECORD
