Metadata-Version: 2.4
Name: font_to_py
Version: 0.44.2
Summary: Tool to convert standard font files to Python source
Home-page: https://github.com/peterhinch/micropython-font-to-py
Author: Peter Hinch
Author-email: peter@ehinch.me.uk
Classifier: Programming Language :: Python :: 3
Classifier: License :: OSI Approved :: MIT License
Requires-Python: >=3.6
License-File: LICENSE
Requires-Dist: freetype-py>=2.4.0
Dynamic: author
Dynamic: author-email
Dynamic: classifier
Dynamic: description
Dynamic: description-content-type
Dynamic: home-page
Dynamic: license-file
Dynamic: requires-dist
Dynamic: requires-python
Dynamic: summary
